.gitignore
AUTHORS.txt
CHANGELOG.rst
CONTRIBUTING.md
COPYING
COPYING.LESSER
MANIFEST.in
README.rst
pyproject.toml
setup.py
tox.ini
.github/workflows/run-tox.yml
bluepyentity/__init__.py
bluepyentity/download.py
bluepyentity/environments.py
bluepyentity/exceptions.py
bluepyentity/token.py
bluepyentity/utils.py
bluepyentity/version.py
bluepyentity.egg-info/PKG-INFO
bluepyentity.egg-info/SOURCES.txt
bluepyentity.egg-info/dependency_links.txt
bluepyentity.egg-info/entry_points.txt
bluepyentity.egg-info/requires.txt
bluepyentity.egg-info/top_level.txt
bluepyentity/app/__init__.py
bluepyentity/app/download.py
bluepyentity/app/info.py
bluepyentity/app/main.py
bluepyentity/app/project.py
bluepyentity/app/token.py
bluepyentity/app/utils.py
bluepyentity/data/__init__.py
bluepyentity/data/prod-forge-nexus.yaml
bluepyentity/data/staging-forge-nexus.yaml
bluepyentity/data/__pycache__/__init__.cpython-38.pyc
bluepyentity/nexus/__init__.py
bluepyentity/nexus/connector.py
bluepyentity/nexus/core.py
bluepyentity/nexus/entity.py
bluepyentity/nexus/factory.py
bluepyentity/nexus/tools.py
doc/Makefile
doc/source/api.rst
doc/source/changelog.rst
doc/source/conf.py
doc/source/index.rst
doc/source/nexusforge.rst
single_cell/forge_access_point.py
tests/test_download.py
tests/test_environments.py
tests/data/.gitignore
tests/nexus/test_connector.py
tests/nexus/test_core.py
tests/nexus/test_entity.py
tests/nexus/test_factory.py
tests/nexus/test_tools.py