Metadata-Version: 2.1
Name: bluepyentity
Version: 0.0.1
Summary: NEXUS Productivity Layer
Home-page: https://github.com/BlueBrain/bluepyentity/
Author: 'Blue Brain Project, EPFL'
License: BBP-internal-confidential
Project-URL: Tracker, https://github.com/BlueBrain/bluepyentity/
Project-URL: Source, https://github.com/BlueBrain/bluepyentity/
Classifier: Development Status :: 2 - Pre-Alpha
Classifier: Intended Audience :: Education
Classifier: Intended Audience :: Science/Research
Classifier: Programming Language :: Python
Classifier: Programming Language :: Python :: 3
Classifier: Programming Language :: Python :: 3.7
Classifier: Programming Language :: Python :: 3.8
Classifier: Topic :: Scientific/Engineering :: Bio-Informatics
Requires-Python: >=3.7
Provides-Extra: docs
Provides-Extra: krb
License-File: COPYING
License-File: COPYING.LESSER
License-File: AUTHORS.txt
